pystruction/__init__.py
pystruction/commands.py
pystruction/templates/.pre-commit-config.txt
pystruction/templates/justfile.txt
pystruction/templates/python-package.txt
pystruction/templates/test.txt
pystruction-0.1.0.dist-info/METADATA
pystruction-0.1.0.dist-info/WHEEL
pystruction-0.1.0.dist-info/entry_points.txt
pystruction-0.1.0.dist-info/RECORD
